cnosdb_connector/__init__.py
cnosdb_connector/client.py
cnosdb_connector/conn.py
cnosdb_connector/cursor.py
cnosdb_connector/error.py
cnosdb_connector/sqlalchemy/__init__.py
cnosdb_connector/sqlalchemy/dialects/__init__.py
cnosdb_connector/sqlalchemy/dialects/base.py
cnosdb_connector/sqlalchemy/dialects/compiler.py
cnos_connector-0.1.9.dist-info/LICENSE
cnos_connector-0.1.9.dist-info/METADATA
cnos_connector-0.1.9.dist-info/WHEEL
cnos_connector-0.1.9.dist-info/entry_points.txt
cnos_connector-0.1.9.dist-info/RECORD
